fls/__init__.py
fls/fls.py
fls-0.0.1.241224.dist-info/LICENSE.txt
fls-0.0.1.241224.dist-info/WHEEL
fls-0.0.1.241224.dist-info/METADATA
fls-0.0.1.241224.dist-info/RECORD
