Metadata-Version: 2.3
Name: fls
Version: 0.0.1.241224
Summary: FLS: A module for matching file system paths against patterns.
Home-page: https://github.com/codyverse/fls
License: MIT
Keywords: file matching, file filter, file patterns, pattern matching, ignore files, file list, path filtering, file selection, gitignore, dockerignore
Author: Andrii Burkatskyi aka andr11b
Author-email: 4ndr116@gmail.com
Requires-Python: >=3.8
Requires-Dist: pytest>=6.0 ; extra == "dev"
Provides-Extra: dev
